Metadata-Version: 2.1
Name: updaterForExe
Version: 1.0
Summary: Updater for exe programs
Home-page: https://github.com/Matthias-coding/updater/
Author: Matthias
Author-email: matthias.harzer03@gmail.com
License: MIT
Download-URL: https://github.com/Matthias-coding/updater/archive/v_1.0.tar.gz
Keywords: Firebase,Pyrebase,Updater
Platform: UNKNOWN
Classifier: Development Status :: 3 - Alpha
Classifier: Intended Audience :: Developers
Classifier: Topic :: Software Development :: Build Tools
Classifier: License :: OSI Approved :: MIT License
Classifier: Programming Language :: Python :: 3.7
